
<sounds root="sfx/">
    <sound name="Destroyed">
        <sample weight="1" path="destroyed.wav" />
    </sound>
    <sound name="Specialsummon">
        <sample weight="1" path="specialsummon.wav" />
    </sound>
    <sound name="ChubbyUp">
        <sample weight="1" path="chubby-up.wav" />
    </sound>
    <sound name="MyMoonMyMan">
        <sample weight="1" path="feedback/my-moon-my-man.wav" />
    </sound>
    <sound name="UseCube">
        <sample weight="1" path="feedback/use-cube.wav" />
    </sound>
</sounds>
